edvart/__init__.py
edvart/data_types.py
edvart/decorators.py
edvart/example_datasets.py
edvart/export_utils.py
edvart/pandas_formatting.py
edvart/plots.py
edvart/report.py
edvart/report_sections/__init__.py
edvart/report_sections/bivariate_analysis.py
edvart/report_sections/code_string_formatting.py
edvart/report_sections/dataset_overview.py
edvart/report_sections/group_analysis.py
edvart/report_sections/multivariate_analysis.py
edvart/report_sections/section_base.py
edvart/report_sections/table_of_contents.py
edvart/report_sections/timeseries_analysis/__init__.py
edvart/report_sections/timeseries_analysis/autocorrelation.py
edvart/report_sections/timeseries_analysis/boxplots_over_time.py
edvart/report_sections/timeseries_analysis/fourier_transform.py
edvart/report_sections/timeseries_analysis/rolling_statistics.py
edvart/report_sections/timeseries_analysis/seasonal_decomposition.py
edvart/report_sections/timeseries_analysis/short_time_ft.py
edvart/report_sections/timeseries_analysis/stationarity_tests.py
edvart/report_sections/timeseries_analysis/time_series_line_plot.py
edvart/report_sections/timeseries_analysis/timeseries_analysis.py
edvart/report_sections/umap.py
edvart/report_sections/univariate_analysis.py
edvart/utils.py
example-datasets/Meteorite_Landings.csv
example-datasets/auto.csv
example-datasets/global_temp.csv
example-datasets/pollution.csv
example-datasets/titanic.csv
edvart-4.0.0.dist-info/LICENSE
edvart-4.0.0.dist-info/METADATA
edvart-4.0.0.dist-info/WHEEL
edvart-4.0.0.dist-info/RECORD
