Metadata-Version: 2.1
Name: edvart
Version: 4.0.0
Summary: Effective data visualization and reporting tool
Home-page: https://github.com/datamole-ai/edvart
License: MIT
Author: Michal Belak
Author-email: michal.belak@datamole.ai
Requires-Python: >=3.9,<3.13
Classifier: License :: OSI Approved :: MIT License
Classifier: Programming Language :: Python :: 3
Classifier: Programming Language :: Python :: 3.9
Classifier: Programming Language :: Python :: 3.10
Classifier: Programming Language :: Python :: 3.11
Classifier: Programming Language :: Python :: 3.12
Provides-Extra: all
Provides-Extra: arrow
Provides-Extra: umap
Requires-Dist: colorlover
Requires-Dist: ipykernel
Requires-Dist: ipywidgets (>=7.5,<9)
Requires-Dist: isort (>=5.10.1,<6.0.0)
Requires-Dist: matplotlib (>=3.3,<4.0)
Requires-Dist: nbconvert (>=7.0.0,<8.0.0)
Requires-Dist: nbformat
Requires-Dist: numba (>=0.59,<0.60) ; extra == "umap" or extra == "all"
Requires-Dist: numpy (>=1.26.0,<2.0.0) ; python_version >= "3.12"
Requires-Dist: numpy ; python_version < "3.12"
Requires-Dist: pandas (>=1.5,<2.3)
Requires-Dist: plotly (>=4.0.0,<6)
Requires-Dist: pyarrow (>=14.0.1,<15.0.0) ; extra == "arrow" or extra == "all"
Requires-Dist: scikit-learn (>=0.22.1)
Requires-Dist: scipy (>=1.11,<2.0) ; python_version >= "3.12"
Requires-Dist: seaborn (>=0.13,<0.14)
Requires-Dist: statsmodels (>0.10.2)
Requires-Dist: strenum (>=0.4.15,<0.5.0) ; python_version < "3.11"
Requires-Dist: umap-learn (>=0.5.4,<0.6.0) ; extra == "umap" or extra == "all"
Project-URL: Repository, https://github.com/datamole-ai/edvart
